ai/backend/appproxy/coordinator/VERSION
ai/backend/appproxy/coordinator/__init__.py
ai/backend/appproxy/coordinator/config.py
ai/backend/appproxy/coordinator/defs.py
ai/backend/appproxy/coordinator/health_checker.py
ai/backend/appproxy/coordinator/pglock.py
ai/backend/appproxy/coordinator/py.typed
ai/backend/appproxy/coordinator/server.py
ai/backend/appproxy/coordinator/types.py
ai/backend/appproxy/coordinator/api/circuit_v1.py
ai/backend/appproxy/coordinator/api/circuit_v2.py
ai/backend/appproxy/coordinator/api/conf.py
ai/backend/appproxy/coordinator/api/endpoint.py
ai/backend/appproxy/coordinator/api/health.py
ai/backend/appproxy/coordinator/api/proxy.py
ai/backend/appproxy/coordinator/api/slot_v1.py
ai/backend/appproxy/coordinator/api/slot_v2.py
ai/backend/appproxy/coordinator/api/types.py
ai/backend/appproxy/coordinator/api/utils.py
ai/backend/appproxy/coordinator/api/worker_v1.py
ai/backend/appproxy/coordinator/api/worker_v2.py
ai/backend/appproxy/coordinator/cli/__main__.py
ai/backend/appproxy/coordinator/cli/config.py
ai/backend/appproxy/coordinator/cli/context.py
ai/backend/appproxy/coordinator/cli/dbschema.py
ai/backend/appproxy/coordinator/cli/dependencies.py
ai/backend/appproxy/coordinator/cli/health.py
ai/backend/appproxy/coordinator/cli/start_server.py
ai/backend/appproxy/coordinator/dependencies/__init__.py
ai/backend/appproxy/coordinator/dependencies/composer.py
ai/backend/appproxy/coordinator/dependencies/bootstrap/__init__.py
ai/backend/appproxy/coordinator/dependencies/bootstrap/composer.py
ai/backend/appproxy/coordinator/dependencies/bootstrap/config.py
ai/backend/appproxy/coordinator/dependencies/infrastructure/__init__.py
ai/backend/appproxy/coordinator/dependencies/infrastructure/composer.py
ai/backend/appproxy/coordinator/dependencies/infrastructure/database.py
ai/backend/appproxy/coordinator/dependencies/infrastructure/etcd.py
ai/backend/appproxy/coordinator/dependencies/infrastructure/redis.py
backend_ai_appproxy_coordinator-26.1.0.dist-info/METADATA
backend_ai_appproxy_coordinator-26.1.0.dist-info/WHEEL
backend_ai_appproxy_coordinator-26.1.0.dist-info/entry_points.txt
backend_ai_appproxy_coordinator-26.1.0.dist-info/namespace_packages.txt
backend_ai_appproxy_coordinator-26.1.0.dist-info/top_level.txt
backend_ai_appproxy_coordinator-26.1.0.dist-info/RECORD
