Metadata-Version: 2.4
Name: backend.ai-appproxy-coordinator
Version: 26.1.0
Summary: Backend.AI AppProxy Coordinator
Home-page: https://github.com/lablup/backend.ai
Author: Lablup Inc. and contributors
License: LGPLv3
Project-URL: Documentation, https://docs.backend.ai/
Project-URL: Source, https://github.com/lablup/backend.ai
Classifier: Intended Audience :: Developers
Classifier: Operating System :: MacOS :: MacOS X
Classifier: Operating System :: POSIX :: Linux
Classifier: Programming Language :: Python
Classifier: Programming Language :: Python :: 3
Classifier: Environment :: No Input/Output (Daemon)
Classifier: Topic :: Scientific/Engineering
Classifier: Topic :: Software Development
Classifier: Development Status :: 5 - Production/Stable
Classifier: Programming Language :: Python :: 3.13
Classifier: License :: OSI Approved :: GNU Lesser General Public License v3 or later (LGPLv3+)
Requires-Python: >=3.13,<3.14
Requires-Dist: Jinja2~=3.1.6
Requires-Dist: PyJWT~=2.10.1
Requires-Dist: SQLAlchemy[postgresql_asyncpg]~=2.0.45
Requires-Dist: aiohttp_cors~=0.8.1
Requires-Dist: aiohttp_jinja2~=1.6
Requires-Dist: aiohttp~=3.13.3
Requires-Dist: aiomonitor~=0.7.0
Requires-Dist: aiotools~=2.2.3
Requires-Dist: alembic~=1.13.2
Requires-Dist: asyncpg>=0.29.0
Requires-Dist: attrs>=25.3
Requires-Dist: backend.ai-appproxy-common==26.1.0
Requires-Dist: backend.ai-cli==26.1.0
Requires-Dist: backend.ai-common==26.1.0
Requires-Dist: backend.ai-logging==26.1.0
Requires-Dist: backend.ai-plugin==26.1.0
Requires-Dist: click~=8.1.7
Requires-Dist: memray~=1.17.2
Requires-Dist: prometheus-client~=0.21.1
Requires-Dist: pydantic[email]~=2.11.3
Requires-Dist: pyroscope-io~=0.8.8
Requires-Dist: python-dateutil>=2.9
Requires-Dist: redis[hiredis]~=7.1.0
Requires-Dist: setproctitle~=1.3.5
Requires-Dist: tenacity>=9.0
Requires-Dist: tomli-w~=1.2.0
Requires-Dist: types-Jinja2
Requires-Dist: types-python-dateutil
Requires-Dist: types-redis
Requires-Dist: uvloop~=0.22.1; sys_platform != "Windows"
Requires-Dist: yarl~=1.19.0
Dynamic: author
Dynamic: classifier
Dynamic: description
Dynamic: description-content-type
Dynamic: home-page
Dynamic: license
Dynamic: project-url
Dynamic: requires-dist
Dynamic: requires-python
Dynamic: summary
